<?xml version="1.0" encoding="UTF-8"?>
<!DOCTYPE markables SYSTEM "markables.dtd">
<markables xmlns="www.eml.org/NameSpaces/sentence">
<markable mmax_level="sentence" id="markable_1" span="word_1..word_36" imported_tag_type="empty" />
<markable mmax_level="sentence" id="markable_2" span="word_37..word_70" imported_tag_type="empty" />
<markable mmax_level="sentence" id="markable_3" span="word_71..word_92" imported_tag_type="empty" />
<markable mmax_level="sentence" id="markable_4" span="word_93..word_125" imported_tag_type="empty" />
<markable mmax_level="sentence" id="markable_5" span="word_126..word_158" imported_tag_type="empty" />
<markable mmax_level="sentence" id="markable_6" span="word_159..word_177" imported_tag_type="empty" />
<markable mmax_level="sentence" id="markable_7" span="word_178..word_203" imported_tag_type="empty" />
<markable mmax_level="sentence" id="markable_8" span="word_204..word_217" imported_tag_type="empty" />
<markable mmax_level="sentence" id="markable_9" span="word_218..word_226" imported_tag_type="empty" />
<markable mmax_level="sentence" id="markable_10" span="word_227..word_265" imported_tag_type="empty" />
<markable mmax_level="sentence" id="markable_11" span="word_266..word_293" imported_tag_type="empty" />
<markable mmax_level="sentence" id="markable_12" span="word_294..word_336" imported_tag_type="empty" />
<markable mmax_level="sentence" id="markable_13" span="word_337..word_369" imported_tag_type="empty" />
<markable mmax_level="sentence" id="markable_14" span="word_370..word_391" imported_tag_type="empty" />
<markable mmax_level="sentence" id="markable_15" span="word_392..word_419" imported_tag_type="empty" />
<markable mmax_level="sentence" id="markable_16" span="word_420..word_443" imported_tag_type="empty" />
<markable mmax_level="sentence" id="markable_17" span="word_444..word_470" imported_tag_type="empty" />
<markable mmax_level="sentence" id="markable_18" span="word_471..word_497" imported_tag_type="empty" />
<markable mmax_level="sentence" id="markable_19" span="word_498..word_515" imported_tag_type="empty" />
<markable mmax_level="sentence" id="markable_20" span="word_516..word_550" imported_tag_type="empty" />
<markable mmax_level="sentence" id="markable_21" span="word_551..word_573" imported_tag_type="empty" />
<markable mmax_level="sentence" id="markable_22" span="word_574..word_590" imported_tag_type="empty" />
<markable mmax_level="sentence" id="markable_23" span="word_591..word_614" imported_tag_type="empty" />
<markable mmax_level="sentence" id="markable_24" span="word_615..word_622" imported_tag_type="empty" />
<markable mmax_level="sentence" id="markable_25" span="word_623..word_654" imported_tag_type="empty" />
<markable mmax_level="sentence" id="markable_26" span="word_655..word_673" imported_tag_type="empty" />
<markable mmax_level="sentence" id="markable_27" span="word_674..word_692" imported_tag_type="empty" />
<markable mmax_level="sentence" id="markable_28" span="word_693..word_723" imported_tag_type="empty" />
<markable mmax_level="sentence" id="markable_29" span="word_724..word_743" imported_tag_type="empty" />
<markable mmax_level="sentence" id="markable_30" span="word_744..word_775" imported_tag_type="empty" />
<markable mmax_level="sentence" id="markable_31" span="word_776..word_797" imported_tag_type="empty" />
<markable mmax_level="sentence" id="markable_32" span="word_798..word_814" imported_tag_type="empty" />
<markable mmax_level="sentence" id="markable_33" span="word_815..word_836" imported_tag_type="empty" />
<markable mmax_level="sentence" id="markable_34" span="word_837..word_843" imported_tag_type="empty" />
<markable mmax_level="sentence" id="markable_35" span="word_844..word_869" imported_tag_type="empty" />
<markable mmax_level="sentence" id="markable_36" span="word_870..word_906" imported_tag_type="empty" />
<markable mmax_level="sentence" id="markable_37" span="word_907..word_922" imported_tag_type="empty" />
<markable mmax_level="sentence" id="markable_38" span="word_923..word_943" imported_tag_type="empty" />
<markable mmax_level="sentence" id="markable_39" span="word_944..word_967" imported_tag_type="empty" />
<markable mmax_level="sentence" id="markable_40" span="word_968..word_1003" imported_tag_type="empty" />
<markable mmax_level="sentence" id="markable_41" span="word_1004..word_1019" imported_tag_type="empty" />
<markable mmax_level="sentence" id="markable_42" span="word_1020..word_1044" imported_tag_type="empty" />
<markable mmax_level="sentence" id="markable_43" span="word_1045..word_1057" imported_tag_type="empty" />
<markable mmax_level="sentence" id="markable_44" span="word_1058..word_1068" imported_tag_type="empty" />
<markable mmax_level="sentence" id="markable_45" span="word_1069..word_1076" imported_tag_type="empty" />
<markable mmax_level="sentence" id="markable_46" span="word_1077..word_1097" imported_tag_type="empty" />
</markables>